swimmers_plot/__init__.py
swimmers_plot/swimmers_plot.py
swimmers_plot-1.0.3.dist-info/LICENSE
swimmers_plot-1.0.3.dist-info/METADATA
swimmers_plot-1.0.3.dist-info/WHEEL
swimmers_plot-1.0.3.dist-info/top_level.txt
swimmers_plot-1.0.3.dist-info/RECORD
